{
  "10,-1": {
    "SourceVersionHash": "YGaLTqKO2C2l7d1dTTKdPVnZ69U=",
    "VersionHash": "spdy+wZ63oB7R4qzBgyemBS9KXI="
  },
  "11,-1": {
    "SourceVersionHash": "YGaLTqKO2C2l7d1dTTKdPVnZ69U=",
    "VersionHash": "spdy+wZ63oB7R4qzBgyemBS9KXI="
  },
  "12,-1": {
    "SourceVersionHash": "A/HTtBCTOVJ7BfEyXGXaSzw4r+c=",
    "VersionHash": "spdy+wZ63oB7R4qzBgyemBS9KXI="
  },
  "10,-10": {
    "SourceVersionHash": "YGaLTqKO2C2l7d1dTTKdPVnZ69U=",
    "VersionHash": "c+ye3ccl9oH/wVNQTIb0OkKhX7k="
  },
  "12,-10": {
    "SourceVersionHash": "A/HTtBCTOVJ7BfEyXGXaSzw4r+c=",
    "VersionHash": "c+ye3ccl9oH/wVNQTIb0OkKhX7k="
  },
  "11,-10": {
    "SourceVersionHash": "YGaLTqKO2C2l7d1dTTKdPVnZ69U=",
    "VersionHash": "c+ye3ccl9oH/wVNQTIb0OkKhX7k="
  },
  "10,-8": {
    "SourceVersionHash": "YGaLTqKO2C2l7d1dTTKdPVnZ69U=",
    "VersionHash": "c+ye3ccl9oH/wVNQTIb0OkKhX7k="
  },
  "10,-9": {
    "SourceVersionHash": "YGaLTqKO2C2l7d1dTTKdPVnZ69U=",
    "VersionHash": "rkLbT0Yq+32gsnS15624aCAJWcY="
  },
  "14,-9": {
    "SourceVersionHash": "A/HTtBCTOVJ7BfEyXGXaSzw4r+c=",
    "VersionHash": "IfKTaZ9yV6V7MaLTZaArvef6lhE="
  },
  "15,-6": {
    "SourceVersionHash": "A/HTtBCTOVJ7BfEyXGXaSzw4r+c=",
    "VersionHash": "IfKTaZ9yV6V7MaLTZaArvef6lhE="
  },
  "11,-8": {
    "SourceVersionHash": "YGaLTqKO2C2l7d1dTTKdPVnZ69U=",
    "VersionHash": "IfKTaZ9yV6V7MaLTZaArvef6lhE="
  },
  "13,-9": {
    "SourceVersionHash": "A/HTtBCTOVJ7BfEyXGXaSzw4r+c=",
    "VersionHash": "IfKTaZ9yV6V7MaLTZaArvef6lhE="
  },
  "11,-9": {
    "SourceVersionHash": "YGaLTqKO2C2l7d1dTTKdPVnZ69U=",
    "VersionHash": "IfKTaZ9yV6V7MaLTZaArvef6lhE="
  },
  "12,-9": {
    "SourceVersionHash": "A/HTtBCTOVJ7BfEyXGXaSzw4r+c=",
    "VersionHash": "IfKTaZ9yV6V7MaLTZaArvef6lhE="
  },
  "14,-5": {
    "SourceVersionHash": "A/HTtBCTOVJ7BfEyXGXaSzw4r+c=",
    "VersionHash": "IfKTaZ9yV6V7MaLTZaArvef6lhE="
  },
  "15,-7": {
    "SourceVersionHash": "A/HTtBCTOVJ7BfEyXGXaSzw4r+c=",
    "VersionHash": "IfKTaZ9yV6V7MaLTZaArvef6lhE="
  },
  "14,-6": {
    "SourceVersionHash": "A/HTtBCTOVJ7BfEyXGXaSzw4r+c=",
    "VersionHash": "IfKTaZ9yV6V7MaLTZaArvef6lhE="
  },
  "13,-7": {
    "SourceVersionHash": "A/HTtBCTOVJ7BfEyXGXaSzw4r+c=",
    "VersionHash": "IfKTaZ9yV6V7MaLTZaArvef6lhE="
  },
  "14,-8": {
    "SourceVersionHash": "A/HTtBCTOVJ7BfEyXGXaSzw4r+c=",
    "VersionHash": "IfKTaZ9yV6V7MaLTZaArvef6lhE="
  },
  "13,-6": {
    "SourceVersionHash": "A/HTtBCTOVJ7BfEyXGXaSzw4r+c=",
    "VersionHash": "IfKTaZ9yV6V7MaLTZaArvef6lhE="
  },
  "13,-5": {
    "SourceVersionHash": "A/HTtBCTOVJ7BfEyXGXaSzw4r+c=",
    "VersionHash": "IfKTaZ9yV6V7MaLTZaArvef6lhE="
  },
  "13,-8": {
    "SourceVersionHash": "A/HTtBCTOVJ7BfEyXGXaSzw4r+c=",
    "VersionHash": "IfKTaZ9yV6V7MaLTZaArvef6lhE="
  },
  "12,-8": {
    "SourceVersionHash": "A/HTtBCTOVJ7BfEyXGXaSzw4r+c=",
    "VersionHash": "IfKTaZ9yV6V7MaLTZaArvef6lhE="
  },
  "13,-4": {
    "SourceVersionHash": "A/HTtBCTOVJ7BfEyXGXaSzw4r+c=",
    "VersionHash": "IfKTaZ9yV6V7MaLTZaArvef6lhE="
  },
  "15,-4": {
    "SourceVersionHash": "A/HTtBCTOVJ7BfEyXGXaSzw4r+c=",
    "VersionHash": "IfKTaZ9yV6V7MaLTZaArvef6lhE="
  },
  "14,-4": {
    "SourceVersionHash": "A/HTtBCTOVJ7BfEyXGXaSzw4r+c=",
    "VersionHash": "IfKTaZ9yV6V7MaLTZaArvef6lhE="
  },
  "11,-7": {
    "SourceVersionHash": "YGaLTqKO2C2l7d1dTTKdPVnZ69U=",
    "VersionHash": "IfKTaZ9yV6V7MaLTZaArvef6lhE="
  },
  "12,-6": {
    "SourceVersionHash": "A/HTtBCTOVJ7BfEyXGXaSzw4r+c=",
    "VersionHash": "IfKTaZ9yV6V7MaLTZaArvef6lhE="
  },
  "15,-5": {
    "SourceVersionHash": "A/HTtBCTOVJ7BfEyXGXaSzw4r+c=",
    "VersionHash": "IfKTaZ9yV6V7MaLTZaArvef6lhE="
  },
  "14,-7": {
    "SourceVersionHash": "A/HTtBCTOVJ7BfEyXGXaSzw4r+c=",
    "VersionHash": "IfKTaZ9yV6V7MaLTZaArvef6lhE="
  },
  "11,-6": {
    "SourceVersionHash": "YGaLTqKO2C2l7d1dTTKdPVnZ69U=",
    "VersionHash": "IfKTaZ9yV6V7MaLTZaArvef6lhE="
  },
  "12,-7": {
    "SourceVersionHash": "A/HTtBCTOVJ7BfEyXGXaSzw4r+c=",
    "VersionHash": "IfKTaZ9yV6V7MaLTZaArvef6lhE="
  },
  "12,-4": {
    "SourceVersionHash": "A/HTtBCTOVJ7BfEyXGXaSzw4r+c=",
    "VersionHash": "cINiU6hTJamXzY4+RQk4R9XxLO8="
  },
  "12,-5": {
    "SourceVersionHash": "A/HTtBCTOVJ7BfEyXGXaSzw4r+c=",
    "VersionHash": "cINiU6hTJamXzY4+RQk4R9XxLO8="
  },
  "11,-4": {
    "SourceVersionHash": "YGaLTqKO2C2l7d1dTTKdPVnZ69U=",
    "VersionHash": "cINiU6hTJamXzY4+RQk4R9XxLO8="
  },
  "11,-5": {
    "SourceVersionHash": "YGaLTqKO2C2l7d1dTTKdPVnZ69U=",
    "VersionHash": "cINiU6hTJamXzY4+RQk4R9XxLO8="
  },
  "10,-3": {
    "SourceVersionHash": "YGaLTqKO2C2l7d1dTTKdPVnZ69U=",
    "VersionHash": "2SVu41bGj/qK1dw89Vm1eSyrdWg="
  },
  "10,-2": {
    "SourceVersionHash": "YGaLTqKO2C2l7d1dTTKdPVnZ69U=",
    "VersionHash": "2SVu41bGj/qK1dw89Vm1eSyrdWg="
  },
  "10,-4": {
    "SourceVersionHash": "YGaLTqKO2C2l7d1dTTKdPVnZ69U=",
    "VersionHash": "2SVu41bGj/qK1dw89Vm1eSyrdWg="
  },
  "12,-3": {
    "SourceVersionHash": "A/HTtBCTOVJ7BfEyXGXaSzw4r+c=",
    "VersionHash": "2SVu41bGj/qK1dw89Vm1eSyrdWg="
  },
  "10,-5": {
    "SourceVersionHash": "YGaLTqKO2C2l7d1dTTKdPVnZ69U=",
    "VersionHash": "2SVu41bGj/qK1dw89Vm1eSyrdWg="
  },
  "12,-2": {
    "SourceVersionHash": "A/HTtBCTOVJ7BfEyXGXaSzw4r+c=",
    "VersionHash": "2SVu41bGj/qK1dw89Vm1eSyrdWg="
  },
  "11,-2": {
    "SourceVersionHash": "YGaLTqKO2C2l7d1dTTKdPVnZ69U=",
    "VersionHash": "2SVu41bGj/qK1dw89Vm1eSyrdWg="
  },
  "11,-3": {
    "SourceVersionHash": "YGaLTqKO2C2l7d1dTTKdPVnZ69U=",
    "VersionHash": "2SVu41bGj/qK1dw89Vm1eSyrdWg="
  },
  "14,-10": {
    "SourceVersionHash": "A/HTtBCTOVJ7BfEyXGXaSzw4r+c=",
    "VersionHash": "zWM0K2fOtaCLihTFn9K/m26wriU="
  },
  "13,-10": {
    "SourceVersionHash": "A/HTtBCTOVJ7BfEyXGXaSzw4r+c=",
    "VersionHash": "zWM0K2fOtaCLihTFn9K/m26wriU="
  },
  "16,-10": {
    "SourceVersionHash": "kgPuwOazuH4GLV4Z3EdfWjwE1fE=",
    "VersionHash": "zWM0K2fOtaCLihTFn9K/m26wriU="
  },
  "16,-9": {
    "SourceVersionHash": "kgPuwOazuH4GLV4Z3EdfWjwE1fE=",
    "VersionHash": "zWM0K2fOtaCLihTFn9K/m26wriU="
  },
  "15,-8": {
    "SourceVersionHash": "A/HTtBCTOVJ7BfEyXGXaSzw4r+c=",
    "VersionHash": "zWM0K2fOtaCLihTFn9K/m26wriU="
  },
  "15,-10": {
    "SourceVersionHash": "A/HTtBCTOVJ7BfEyXGXaSzw4r+c=",
    "VersionHash": "zWM0K2fOtaCLihTFn9K/m26wriU="
  },
  "15,-9": {
    "SourceVersionHash": "A/HTtBCTOVJ7BfEyXGXaSzw4r+c=",
    "VersionHash": "zWM0K2fOtaCLihTFn9K/m26wriU="
  },
  "13,-1": {
    "SourceVersionHash": "A/HTtBCTOVJ7BfEyXGXaSzw4r+c=",
    "VersionHash": "raNjqa4iLQnHX2Ukqz0Wl8ccd/k="
  },
  "14,-1": {
    "SourceVersionHash": "A/HTtBCTOVJ7BfEyXGXaSzw4r+c=",
    "VersionHash": "raNjqa4iLQnHX2Ukqz0Wl8ccd/k="
  },
  "15,-1": {
    "SourceVersionHash": "A/HTtBCTOVJ7BfEyXGXaSzw4r+c=",
    "VersionHash": "RekZhqb+/hj/20vz81Igr2hTCJI="
  },
  "13,-3": {
    "SourceVersionHash": "A/HTtBCTOVJ7BfEyXGXaSzw4r+c=",
    "VersionHash": "7bCkFZyJ4twsv7E+gQg3+K6rSDQ="
  },
  "14,-3": {
    "SourceVersionHash": "A/HTtBCTOVJ7BfEyXGXaSzw4r+c=",
    "VersionHash": "3Pm6upkKRa4WRajLkdqNAlTDdKY="
  },
  "15,-2": {
    "SourceVersionHash": "A/HTtBCTOVJ7BfEyXGXaSzw4r+c=",
    "VersionHash": "3Pm6upkKRa4WRajLkdqNAlTDdKY="
  },
  "14,-2": {
    "SourceVersionHash": "A/HTtBCTOVJ7BfEyXGXaSzw4r+c=",
    "VersionHash": "3Pm6upkKRa4WRajLkdqNAlTDdKY="
  },
  "13,-2": {
    "SourceVersionHash": "A/HTtBCTOVJ7BfEyXGXaSzw4r+c=",
    "VersionHash": "3Pm6upkKRa4WRajLkdqNAlTDdKY="
  },
  "15,-3": {
    "SourceVersionHash": "A/HTtBCTOVJ7BfEyXGXaSzw4r+c=",
    "VersionHash": "3Pm6upkKRa4WRajLkdqNAlTDdKY="
  },
  "19,-9": {
    "SourceVersionHash": "kgPuwOazuH4GLV4Z3EdfWjwE1fE=",
    "VersionHash": "bI/kdyVcafnuRutIfiMHHNYrwf8="
  },
  "19,-10": {
    "SourceVersionHash": "kgPuwOazuH4GLV4Z3EdfWjwE1fE=",
    "VersionHash": "isyPfZRRA4fu9zzg3GpKin9G/9E="
  },
  "10,-6": {
    "SourceVersionHash": "YGaLTqKO2C2l7d1dTTKdPVnZ69U=",
    "VersionHash": "nw5b4ypzaCtw5H+IXSt8Vy9kM3g="
  },
  "10,-7": {
    "SourceVersionHash": "YGaLTqKO2C2l7d1dTTKdPVnZ69U=",
    "VersionHash": "nw5b4ypzaCtw5H+IXSt8Vy9kM3g="
  },
  "18,-10": {
    "SourceVersionHash": "kgPuwOazuH4GLV4Z3EdfWjwE1fE=",
    "VersionHash": "CIIXfadasXSNatmJu2wm9/I6H7Y="
  },
  "18,-9": {
    "SourceVersionHash": "kgPuwOazuH4GLV4Z3EdfWjwE1fE=",
    "VersionHash": "CIIXfadasXSNatmJu2wm9/I6H7Y="
  },
  "17,-9": {
    "SourceVersionHash": "kgPuwOazuH4GLV4Z3EdfWjwE1fE=",
    "VersionHash": "CIIXfadasXSNatmJu2wm9/I6H7Y="
  },
  "17,-10": {
    "SourceVersionHash": "kgPuwOazuH4GLV4Z3EdfWjwE1fE=",
    "VersionHash": "CIIXfadasXSNatmJu2wm9/I6H7Y="
  }
}