{
  "21,13": {
    "SourceVersionHash": "kgPuwOazuH4GLV4Z3EdfWjwE1fE=",
    "VersionHash": "ED8MNLffQQTyejBSfAuMugPd8uM="
  },
  "22,14": {
    "SourceVersionHash": "kgPuwOazuH4GLV4Z3EdfWjwE1fE=",
    "VersionHash": "ED8MNLffQQTyejBSfAuMugPd8uM="
  },
  "22,13": {
    "SourceVersionHash": "kgPuwOazuH4GLV4Z3EdfWjwE1fE=",
    "VersionHash": "ED8MNLffQQTyejBSfAuMugPd8uM="
  },
  "21,14": {
    "SourceVersionHash": "kgPuwOazuH4GLV4Z3EdfWjwE1fE=",
    "VersionHash": "ED8MNLffQQTyejBSfAuMugPd8uM="
  },
  "23,14": {
    "SourceVersionHash": "kgPuwOazuH4GLV4Z3EdfWjwE1fE=",
    "VersionHash": "ED8MNLffQQTyejBSfAuMugPd8uM="
  },
  "23,13": {
    "SourceVersionHash": "kgPuwOazuH4GLV4Z3EdfWjwE1fE=",
    "VersionHash": "ED8MNLffQQTyejBSfAuMugPd8uM="
  },
  "21,15": {
    "SourceVersionHash": "kgPuwOazuH4GLV4Z3EdfWjwE1fE=",
    "VersionHash": "ED8MNLffQQTyejBSfAuMugPd8uM="
  },
  "23,15": {
    "SourceVersionHash": "kgPuwOazuH4GLV4Z3EdfWjwE1fE=",
    "VersionHash": "ED8MNLffQQTyejBSfAuMugPd8uM="
  },
  "22,12": {
    "SourceVersionHash": "kgPuwOazuH4GLV4Z3EdfWjwE1fE=",
    "VersionHash": "ED8MNLffQQTyejBSfAuMugPd8uM="
  },
  "21,12": {
    "SourceVersionHash": "kgPuwOazuH4GLV4Z3EdfWjwE1fE=",
    "VersionHash": "ED8MNLffQQTyejBSfAuMugPd8uM="
  },
  "21,16": {
    "SourceVersionHash": "LL8TICbMgawbLmTEkfIVIonUkrE=",
    "VersionHash": "ED8MNLffQQTyejBSfAuMugPd8uM="
  },
  "20,14": {
    "SourceVersionHash": "kgPuwOazuH4GLV4Z3EdfWjwE1fE=",
    "VersionHash": "ED8MNLffQQTyejBSfAuMugPd8uM="
  },
  "20,13": {
    "SourceVersionHash": "kgPuwOazuH4GLV4Z3EdfWjwE1fE=",
    "VersionHash": "ED8MNLffQQTyejBSfAuMugPd8uM="
  },
  "23,16": {
    "SourceVersionHash": "LL8TICbMgawbLmTEkfIVIonUkrE=",
    "VersionHash": "ED8MNLffQQTyejBSfAuMugPd8uM="
  },
  "22,15": {
    "SourceVersionHash": "kgPuwOazuH4GLV4Z3EdfWjwE1fE=",
    "VersionHash": "ED8MNLffQQTyejBSfAuMugPd8uM="
  },
  "22,16": {
    "SourceVersionHash": "LL8TICbMgawbLmTEkfIVIonUkrE=",
    "VersionHash": "ED8MNLffQQTyejBSfAuMugPd8uM="
  },
  "20,16": {
    "SourceVersionHash": "LL8TICbMgawbLmTEkfIVIonUkrE=",
    "VersionHash": "IxwCQ1s2jeUrQstr0+fGTtKE1KI="
  },
  "20,15": {
    "SourceVersionHash": "kgPuwOazuH4GLV4Z3EdfWjwE1fE=",
    "VersionHash": "IxwCQ1s2jeUrQstr0+fGTtKE1KI="
  },
  "20,12": {
    "SourceVersionHash": "kgPuwOazuH4GLV4Z3EdfWjwE1fE=",
    "VersionHash": "IxwCQ1s2jeUrQstr0+fGTtKE1KI="
  },
  "23,12": {
    "SourceVersionHash": "kgPuwOazuH4GLV4Z3EdfWjwE1fE=",
    "VersionHash": "6nJEurjnKJmjhH9rMZUe40vuhFw="
  },
  "24,11": {
    "SourceVersionHash": "LL8TICbMgawbLmTEkfIVIonUkrE=",
    "VersionHash": "6nJEurjnKJmjhH9rMZUe40vuhFw="
  },
  "29,10": {
    "SourceVersionHash": "m54voCYVlIZ2e4MBL/aowY6oDRM=",
    "VersionHash": "mTAVZIvJpZkamzG1W95PdwblVbA="
  },
  "29,11": {
    "SourceVersionHash": "m54voCYVlIZ2e4MBL/aowY6oDRM=",
    "VersionHash": "mTAVZIvJpZkamzG1W95PdwblVbA="
  },
  "27,10": {
    "SourceVersionHash": "LL8TICbMgawbLmTEkfIVIonUkrE=",
    "VersionHash": "mTAVZIvJpZkamzG1W95PdwblVbA="
  },
  "28,11": {
    "SourceVersionHash": "m54voCYVlIZ2e4MBL/aowY6oDRM=",
    "VersionHash": "mTAVZIvJpZkamzG1W95PdwblVbA="
  },
  "27,11": {
    "SourceVersionHash": "LL8TICbMgawbLmTEkfIVIonUkrE=",
    "VersionHash": "mTAVZIvJpZkamzG1W95PdwblVbA="
  },
  "28,10": {
    "SourceVersionHash": "m54voCYVlIZ2e4MBL/aowY6oDRM=",
    "VersionHash": "mTAVZIvJpZkamzG1W95PdwblVbA="
  },
  "21,17": {
    "SourceVersionHash": "LL8TICbMgawbLmTEkfIVIonUkrE=",
    "VersionHash": "0bFFsQ3mW1ra/kJDroedUgRCQcY="
  },
  "22,18": {
    "SourceVersionHash": "LL8TICbMgawbLmTEkfIVIonUkrE=",
    "VersionHash": "0bFFsQ3mW1ra/kJDroedUgRCQcY="
  },
  "22,17": {
    "SourceVersionHash": "LL8TICbMgawbLmTEkfIVIonUkrE=",
    "VersionHash": "0bFFsQ3mW1ra/kJDroedUgRCQcY="
  },
  "21,18": {
    "SourceVersionHash": "LL8TICbMgawbLmTEkfIVIonUkrE=",
    "VersionHash": "0bFFsQ3mW1ra/kJDroedUgRCQcY="
  },
  "22,19": {
    "SourceVersionHash": "LL8TICbMgawbLmTEkfIVIonUkrE=",
    "VersionHash": "B7KpOc8qDsFRWBNsp2t9IM8Ll5I="
  },
  "21,19": {
    "SourceVersionHash": "LL8TICbMgawbLmTEkfIVIonUkrE=",
    "VersionHash": "B7KpOc8qDsFRWBNsp2t9IM8Ll5I="
  },
  "20,18": {
    "SourceVersionHash": "LL8TICbMgawbLmTEkfIVIonUkrE=",
    "VersionHash": "B7KpOc8qDsFRWBNsp2t9IM8Ll5I="
  },
  "20,19": {
    "SourceVersionHash": "LL8TICbMgawbLmTEkfIVIonUkrE=",
    "VersionHash": "B7KpOc8qDsFRWBNsp2t9IM8Ll5I="
  },
  "23,18": {
    "SourceVersionHash": "LL8TICbMgawbLmTEkfIVIonUkrE=",
    "VersionHash": "B7KpOc8qDsFRWBNsp2t9IM8Ll5I="
  },
  "23,17": {
    "SourceVersionHash": "LL8TICbMgawbLmTEkfIVIonUkrE=",
    "VersionHash": "B7KpOc8qDsFRWBNsp2t9IM8Ll5I="
  },
  "20,17": {
    "SourceVersionHash": "LL8TICbMgawbLmTEkfIVIonUkrE=",
    "VersionHash": "B7KpOc8qDsFRWBNsp2t9IM8Ll5I="
  },
  "23,19": {
    "SourceVersionHash": "LL8TICbMgawbLmTEkfIVIonUkrE=",
    "VersionHash": "Izu9Ti42Z3r/BOuMKzjIuXZiFIo="
  },
  "24,10": {
    "SourceVersionHash": "LL8TICbMgawbLmTEkfIVIonUkrE=",
    "VersionHash": "Nx00TElQ/1ftNeRG8nbanaBuaPg="
  },
  "26,11": {
    "SourceVersionHash": "LL8TICbMgawbLmTEkfIVIonUkrE=",
    "VersionHash": "Nx00TElQ/1ftNeRG8nbanaBuaPg="
  },
  "26,10": {
    "SourceVersionHash": "LL8TICbMgawbLmTEkfIVIonUkrE=",
    "VersionHash": "Nx00TElQ/1ftNeRG8nbanaBuaPg="
  },
  "25,10": {
    "SourceVersionHash": "LL8TICbMgawbLmTEkfIVIonUkrE=",
    "VersionHash": "Nx00TElQ/1ftNeRG8nbanaBuaPg="
  },
  "25,11": {
    "SourceVersionHash": "LL8TICbMgawbLmTEkfIVIonUkrE=",
    "VersionHash": "Nx00TElQ/1ftNeRG8nbanaBuaPg="
  }
}